setup.py
rohan_indian_states_25/__init__.py
rohan_indian_states_25/asgi.py
rohan_indian_states_25/settings.py
rohan_indian_states_25/urls.py
rohan_indian_states_25/wsgi.py
rohan_indian_states_25.egg-info/PKG-INFO
rohan_indian_states_25.egg-info/SOURCES.txt
rohan_indian_states_25.egg-info/dependency_links.txt
rohan_indian_states_25.egg-info/requires.txt
rohan_indian_states_25.egg-info/top_level.txt
rpt1/__init__.py
rpt1/admin.py
rpt1/apps.py
rpt1/fields.py
rpt1/forms.py
rpt1/models.py
rpt1/states.py
rpt1/tests.py
rpt1/views.py
rpt1/migrations/__init__.py