Metadata-Version: 2.1
Name: rohan_indian_states_25
Version: 0.1
Summary: A Django app that provides Indian state choices as a model and form field.
Author: Rohan Patil
Author-email: rohanrpatil77@gmail.com
License: MIT
Classifier: Framework :: Django
Classifier: Programming Language :: Python :: 3
Requires-Dist: django
